polytopewalk.cpython-39-x86_64-linux-gnu.so
polytopewalk-1.1.0.dist-info/WHEEL
polytopewalk-1.1.0.dist-info/RECORD
polytopewalk-1.1.0.dist-info/METADATA
polytopewalk-1.1.0.dist-info/licenses/LICENSE
polytopewalk.libs/libglpk-71fa9d4d.so.36.0.1
