Metadata-Version: 2.2
Name: polytopewalk
Version: 1.1.0
Summary: Open Source Implementation of MCMC Polytope Walks
Keywords: MCMC,Dikin Walk,Vaidya Walk,John Walk,Lee Sidford Walk,Sparse,Sampling
Author-Email: Benny Sun <benny.sun@duke.edu>, Yuansi Chen <yuansi.chen@stat.math.ethz.ch>
Classifier: Intended Audience :: Science/Research
Classifier: Intended Audience :: Developers
Classifier: License :: OSI Approved :: MIT License
Classifier: Programming Language :: C
Classifier: Programming Language :: Python
Classifier: Programming Language :: Python :: 3
Classifier: Programming Language :: Python :: 3.9
Classifier: Programming Language :: Python :: 3.10
Classifier: Programming Language :: Python :: 3.11
Classifier: Programming Language :: Python :: 3.12
Classifier: Programming Language :: Python :: 3.13
Classifier: Programming Language :: Python :: 3 :: Only
Classifier: Programming Language :: Python :: Implementation :: CPython
Classifier: Topic :: Software Development
Classifier: Topic :: Scientific/Engineering
Classifier: Operating System :: Microsoft :: Windows
Classifier: Operating System :: Unix
Classifier: Operating System :: MacOS
Requires-Python: >=3.9
Requires-Dist: numpy>=1.20
Requires-Dist: scipy>=1.6.0
